opentelemetry/instrumentation/togetherai/__init__.py
opentelemetry/instrumentation/togetherai/config.py
opentelemetry/instrumentation/togetherai/utils.py
opentelemetry/instrumentation/togetherai/version.py
opentelemetry_instrumentation_togetherai-0.21.2.dist-info/METADATA
opentelemetry_instrumentation_togetherai-0.21.2.dist-info/WHEEL
opentelemetry_instrumentation_togetherai-0.21.2.dist-info/entry_points.txt
opentelemetry_instrumentation_togetherai-0.21.2.dist-info/RECORD
